{"data":{"site":{"siteMetadata":{"title":"JλO","author":"Jean-Louis Leysens"}},"markdownRemark":{"id":"ede28958-22e8-5ab7-b840-08d6894bd3da","excerpt":"The Last of Us (TLOU) part II was released on June 19th 2020. The studio\nthat masterminded its creation, Naughty Dog, has dedicated an enormous amount\nof…","html":"<p>The Last of Us (TLOU) part II was released on June 19th 2020. The studio\nthat masterminded its creation, Naughty Dog, has dedicated an enormous amount\nof resources to creating this game. And I think what they have created reaches\nbeyond the scope of video game and deep into the realm of art and story telling.\nI would like to unpack this further, but as a preface I would like to state\nfrom the outset that I did not like a lot of the decisions that were made for this\ngame. I did not like it, but I still marvel at it.</p>\n<p>Before going any further, please note that <strong>this discussion contains spoilers</strong>.</p>\n<h3>Notes</h3>\n<ol>\n<li>SkillUp’s <a href=\"https://www.youtube.com/watch?v=GB20A8CitRU&#x26;\">review of the game</a>.</li>\n</ol>","frontmatter":{"title":"The Last of Us Part II","date":"June 28, 2020"}}},"pageContext":{"isCreatedByStatefulCreatePages":false,"category":"video-games","slug":"/video-games/tlou-part-ii/","previous":null,"next":null}}